GSIM.v
`timescale 1ns/10ps
module GSIM ( clk, reset, in_en, b_in, out_valid, x_out);

    input   clk ;
    input   reset ;
    input   in_en;
    output  out_valid;
    input   [15:0]  b_in;
    output  [31:0]  x_out;

    parameter RUN = 50; //after this run number, the out_valid will be pulled up

    wire [32-1:0] x;
    wire [32-1:0] x1, x2, x3, x4, x5, x6;
    wire [16-1:0] b;
    reg  [4-1:0]  cycle_count_r;
    reg  [4-1:0]  cycle_count_w;
    reg  [6-1:0]  run_count_r;
    reg  [6-1:0]  run_count_w;
    wire          start;

    register_file register_file (
        .clk_in(clk),
        .rst_in(reset),
        .en_in(in_en),
        .b_in(b_in),
        .x_in(x),
        .b_out(b),
        .x1_out(x1),
        .x2_out(x2),
        .x3_out(x3),
        .x4_out(x4),
        .x5_out(x5),
        .x6_out(x6),
        .start_out(start)
    );

    Computation_Unit Computation_Unit (
        .clk(clk),
        .reset(reset),
        .b({b, 16'd0}),
        .x_0(x1),
        .x_1(x2),
        .x_2(x3),
        .x_3(x4),
        .x_4(x5),
        .x_5(x6),
        .x_new(x)
    );

    //Handle cycle_count_r, initialize when in_en is high; otherwise, count the cycle number
    always @(*) begin
        if (in_en == 1'b1)
            cycle_count_w = 4'd0;
        else
            cycle_count_w = cycle_count_r + 1;
    end

    always @(posedge clk) begin
        cycle_count_r <= cycle_count_w;
    end

    //Handle run_count_r, initialize when in_en is high; otherwise, when cycle_count_r is 15, run_count_r + 1
    always @(*) begin
        if (in_en == 1'b1)
            run_count_w = 6'd0;
        else if (cycle_count_r == 4'd15)
            run_count_w = run_count_r + 1;
        else
            run_count_w = run_count_r;
    end

    always @(posedge clk) begin
        run_count_r <= run_count_w;
    end

    assign x_out     = x; //just output the x computed
    assign out_valid = (start && ((run_count_r == RUN && cycle_count_r >= 4'd1) || (run_count_r == RUN + 1 && cycle_count_r == 4'd0))) ? 1'b1 : 1'b0; //pulled up when run_count_r achieve RUN

endmodule

/*Register file, used for shiftedly outputing the needed x and b for computation unit*/
module register_file (
    clk_in,
    rst_in,
    en_in,
    b_in,
    x_in,
    b_out,
    x1_out,
    x2_out,
    x3_out,
    x4_out,
    x5_out,
    x6_out,
    start_out
);

    input           clk_in, rst_in, en_in;
    input  [16-1:0] b_in;
    input  [32-1:0] x_in;
    output [16-1:0] b_out;
    output [32-1:0] x1_out, x2_out, x3_out, x4_out, x5_out, x6_out;
    output          start_out;

    reg    [16-1:0] b_r[0:16-1];
    reg    [16-1:0] b_w[0:16-1];
    
    reg    [32-1:0] x_r[0:16-1];
    reg    [32-1:0] x_w[0:16-1];

    reg    [4-1:0] count_r;
    reg    [4-1:0] count_w;

    reg            start_r;
    reg            start_w;

    reg            delay_start_r;
    reg            delay_start_w;

    integer i;

    //Handle b_r, when en_in == 1'b1, read b_in and shift to lower index; otherwise, shift circularly
    always @(*) begin
        if (en_in == 1'b1) begin
            b_w[15] = b_in;
            for (i = 0; i < 16 - 1; i = i + 1) begin
                b_w[i] = b_r[i+1];
            end
        end
        else begin
            b_w[15] = b_r[0];
            for (i = 0; i < 16 - 1; i = i + 1) begin
                b_w[i] = b_r[i+1];
            end
        end
    end

    always @(posedge clk_in) begin
        for (i = 0; i < 16; i = i + 1) begin
            b_r[i] <= b_w[i];
        end
    end

    //Handle x_r, when reset is high, reset to initial values; else store their values until start_r is high, note that the delay_start_r is due to the pipeline of computational unit.
    always @(*) begin
        if (delay_start_r == 1'b1) begin //shift and store x_in to x[14]
            x_w[15] = x_r[0];
            x_w[14] = x_in;
            for (i = 0; i < 16 - 2; i = i + 1) begin
                x_w[i] = x_r[i+1];
            end
        end
        else if (start_r == 1'b1) begin //shift but not store x_in
            x_w[15] = x_r[0];
            for (i = 0; i < 16 - 1; i = i + 1) begin
                x_w[i] = x_r[i+1];
            end
        end
        else begin
            for (i = 0; i < 16; i = i + 1) begin
                x_w[i] = x_r[i];
            end
        end
    end

    always @(posedge clk_in or posedge rst_in) begin
        if (rst_in == 1'b1) begin //Run initial_x_value_generator.py for random initial values
            x_r[0] <= 32'd0;
            x_r[1] <= 32'd0;
            x_r[2] <= 32'd0;
            x_r[3] <= 32'd0;
            x_r[4] <= 32'd0;
            x_r[5] <= 32'd0;
            x_r[6] <= 32'd0;
            x_r[7] <= 32'd0;
            x_r[8] <= 32'd0;
            x_r[9] <= 32'd0;
            x_r[10] <= 32'd0;
            x_r[11] <= 32'd0;
            x_r[12] <= 32'd0;
            x_r[13] <= 32'd0;
            x_r[14] <= 32'd0;
            x_r[15] <= 32'd0;
        end
        else begin
            for (i = 0; i < 16; i = i + 1) begin
                x_r[i] <= x_w[i];
            end
        end
    end

    //Handle count_r, start to count right after the moment en_in is pulled to high; before that, set to 0
    always @(*) begin
        count_w = count_r + 1;
    end

    always @(posedge clk_in or posedge rst_in) begin
        if (start_r == 1'b1 || en_in == 1'b1)
            count_r <= count_w;
        else
            count_r <= 4'd0;
    end

    //Handle start_r, if en_in is high, the counter start, and if the counter arrives at 15, set start_r to shift x_r
    always @(*) begin
        if (count_r == 4'd15)
            start_w = 1'b1;
        else
            start_w = start_r;
    end

    always @(posedge clk_in or posedge rst_in) begin
        if (rst_in == 1'b1)
            start_r <= 1'b0;
        else
            start_r <= start_w;
    end

    //Handle delay_start_r, delayed from start_r by one cycle because of the computational unit delay
    always @(*) begin
        delay_start_w = start_r;
    end

    always @(posedge clk_in or posedge rst_in) begin
        if (rst_in == 1'b1)
            delay_start_r <= 1'b0;
        else
            delay_start_r <= delay_start_w;
    end

    assign b_out     = b_r[0];                               //always output b_r[0] and shift from higher index
    assign x1_out    = (count_r == 4'd15) ? 32'd0 : x_r[1];  //see ppt P.4 for this implementation
    assign x2_out    = (count_r == 4'd0)  ? 32'd0 : x_r[15]; //see ppt P.4 for this implementation
    assign x3_out    = (count_r >= 4'd14) ? 32'd0 : x_r[2];  //see ppt P.4 for this implementation
    assign x4_out    = (count_r <= 4'd1)  ? 32'd0 : x_r[14]; //see ppt P.4 for this implementation
    assign x5_out    = (count_r >= 4'd13) ? 32'd0 : x_r[3];  //see ppt P.4 for this implementation
    assign x6_out    = (count_r <= 4'd2)  ? 32'd0 : x_r[13]; //see ppt P.4 for this implementation
    assign start_out = start_r;                              //To let GSIM know the out_valid can be pulled up

endmodule


/* ======== 說明 ========
以下的code是參考Exercise.pdf p.9 右下角的架構圖來完成的
不過我把他切成2個stage的pipeline，前後2個stage的critical path都差不多是連續4個32bit加法所要的時間
我自己測了幾個test pattern，答案是正確的(雖然不能百分百保證沒問題)，然後誤差也很小，看能不能達到rank A(不能就再改一下除法器)
 ================================*/

module Computation_Unit (clk, reset, b, x_0, x_1, x_2, x_3, x_4, x_5, x_new); // compute the result in 2 cycles 
    input                clk, reset;               // Compute : b + 13(x_0 + x_1) - 6(x_2 + x_3) + (x_4 + x_5)
    input signed  [31:0] b;                    
    input signed  [31:0] x_0, x_1, x_2, x_3, x_4, x_5;
    output signed [31:0] x_new;

    //================= Parameter Declaration ======================
    wire signed   [31:0] x_0_1, x_2_3, x_4_5, x_plus_b, x_sub_6, DFF_nxt;
    wire signed   [31:0] x_0_1_mul4, x_0_1_mul8, x_0_1_mul13, x_2_3_mul2, x_2_3_mul4, x_2_3_mul6;
    reg signed    [31:0] DFF;

    //===================== Combinational ==========================
    assign x_0_1 = x_0 + x_1;
    assign x_2_3 = x_2 + x_3;
    assign x_4_5 = x_4 + x_5;
    assign x_plus_b = x_4_5 + b;
    assign x_0_1_mul4 = {x_0_1[29:0], 2'b0};
    assign x_0_1_mul8 = {x_0_1[28:0], 3'b0};
    assign x_0_1_mul13 = x_0_1 + x_0_1_mul4 + x_0_1_mul8;
    assign x_2_3_mul2 = {x_2_3[30:0], 1'b0};
    assign x_2_3_mul4 = {x_2_3[29:0], 2'b0};
    assign x_2_3_mul6 = x_2_3_mul2 + x_2_3_mul4;
    assign x_sub_6 = x_plus_b - x_2_3_mul6;
    assign DFF_nxt = x_0_1_mul13 + x_sub_6;

    division_20 div0 (.in(DFF), .out(x_new));

    //======================= Sequential ===========================
    always @(posedge clk or posedge reset) begin
        if (reset) DFF <= 32'b0;
        else DFF <= DFF_nxt;
    end

endmodule

module division_20 (in, out);  // multiply by (2^-5 + 2^-6 + 2^-9 + 2^-10 + 2^-13 + 2^-14 
    input  [31:0] in;          //            + 2^-17 + 2^-18 + 2^-21 + 2^-22 + 2^-25 + 2^-26)
    output [31:0] out;
    wire [33:0] x_5, x_6, x_9, x_10, x_13, x_14, x_17, x_18, x_21, x_22, x_25, x_26;
    wire [33:0] x_5_6, x_9_10, x_13_14, x_17_18, x_21_22, x_25_26, x_5to10, x_13to18, x_21to26;
    assign x_5 = {{5{in[31]}}, in[31:3]};
    assign x_6 = {{6{in[31]}}, in[31:4]};
    assign x_9 = {{9{in[31]}}, in[31:7]};
    assign x_10 = {{10{in[31]}}, in[31:8]};
    assign x_13 = {{13{in[31]}}, in[31:11]};
    assign x_14 = {{14{in[31]}}, in[31:12]};
    assign x_17 = {{17{in[31]}}, in[31:15]};
    assign x_18 = {{18{in[31]}}, in[31:16]}; 
    assign x_21 = {{21{in[31]}}, in[31:19]};
    assign x_22 = {{22{in[31]}}, in[31:20]};
    assign x_25 = {{25{in[31]}}, in[31:23]};
    assign x_26 = {{26{in[31]}}, in[31:24]}; 
    assign x_5_6 = x_5 + x_6;
    assign x_9_10 = x_9 + x_10;
    assign x_13_14 = x_13 + x_14;
    assign x_17_18 = x_17 + x_18;
    assign x_21_22 = x_21 + x_22;
    assign x_25_26 = x_25 + x_26;
    assign x_5to10 = x_5_6 + x_9_10;
    assign x_13to18 = x_13_14 + x_17_18;
    assign x_21to26 = x_21_22 + x_25_26;
    assign out = x_5to10[33:2] + x_13to18[33:2] + x_21to26[33:2];
endmodule

testfixture2.v
`timescale 1ns/10ps
`define CYCLE    4           	         // Modify your clock period here
`define SDFFILE  "./GSIM_syn.sdf"	      // Modify your sdf file name
`define PAT      "./pattern2.dat"    
`define DEL      1
module test;
parameter N_PAT   = 16;

reg   clk ;
reg   reset ;
reg   in_en;
reg   [15:0]  b_in;
wire  out_valid;
wire  [31:0]  x_out;

reg   [15:0]  pat_mem   [0:N_PAT-1];
reg   [31:0]  x         [0:N_PAT-1];
reg   [15:0]  b         [0:N_PAT-1];
reg   [15:0]  b_tmp;
integer       loop, i, j, out_f;
reg           stop;
real  Mb [0:15];
real  x_f[0:15];
real  SquareError, error, temp;


   GSIM GSIM( .clk(clk), .reset(reset), .in_en(in_en), .b_in(b_in),
              .out_valid(out_valid), .x_out(x_out));
   

`ifdef SDF
   initial $sdf_annotate(`SDFFILE, GSIM);
`endif

initial	$readmemh (`PAT, pat_mem);


initial begin
   clk         = 1'b0;
   reset       = 1'b0;
   in_en       = 1'b0;   
   b_in        = 'hz;
   stop        = 1'b0;   
   loop        = 0;
end

always begin #(`CYCLE/2) clk = ~clk; end

initial begin
$dumpfile("GSIM.vcd");
$dumpvars;
//$fsdbDumpfile("GSIM.fsdb");
//$fsdbDumpvars;

   out_f = $fopen("out.dat");
   if (out_f == 0) begin
        $display("Output file open error !");
        $finish;
   end
end


initial begin
   @(posedge clk)  #`DEL  reset = 1'b1;
   #`CYCLE                reset = 1'b0;
   
   @(posedge clk)  #`DEL i=0;
    while (i < N_PAT) begin               
         b_in  = pat_mem[i];
         b[i]  = pat_mem[i];
         in_en = 1'b1;
         i=i+1;                  
      @(posedge clk); #`DEL; 
    end     
    in_en = 1'b0;  b_in=16'hz;
end


always @(posedge clk)begin
   if(loop <16)begin
      if(out_valid)begin
         x[loop]=x_out;
         loop=loop+1;
      end
   end
   else begin
         stop=1;
   end
end


initial begin
   @(posedge stop) 
     for (j=0;j<=15;j=j+1)begin
        if(x[j][31]==1) begin   x_f[j]=~x[j] +1'b1;    x_f[j] =-x_f[j]/65536;  end
        else            begin   x_f[j]= x[j];          x_f[j] = x_f[j]/65536;  end
     end
                          
     Mb[0 ]= 20*x_f[0 ]-13*x_f[1 ]+ 6*x_f[2 ]-   x_f[3 ];
     Mb[1 ]=-13*x_f[0 ]+20*x_f[1 ]-13*x_f[2 ]+ 6*x_f[3 ]-   x_f[4 ];
     Mb[2 ]=  6*x_f[0 ]-13*x_f[1 ]+20*x_f[2 ]-13*x_f[3 ]+ 6*x_f[4 ]-  x_f[5 ];      
     Mb[3 ]=   -x_f[0 ]+ 6*x_f[1 ]-13*x_f[2 ]+20*x_f[3 ]-13*x_f[4 ]+6*x_f[5 ]-x_f[6 ];      
     Mb[4 ]=   -x_f[1 ]+ 6*x_f[2 ]-13*x_f[3 ]+20*x_f[4 ]-13*x_f[5 ]+6*x_f[6 ]-x_f[7 ];
     Mb[5 ]=   -x_f[2 ]+ 6*x_f[3 ]-13*x_f[4 ]+20*x_f[5 ]-13*x_f[6 ]+6*x_f[7 ]-x_f[8 ];                    
     Mb[6 ]=   -x_f[3 ]+ 6*x_f[4 ]-13*x_f[5 ]+20*x_f[6 ]-13*x_f[7 ]+6*x_f[8 ]-x_f[9 ];
     Mb[7 ]=   -x_f[4 ]+ 6*x_f[5 ]-13*x_f[6 ]+20*x_f[7 ]-13*x_f[8 ]+6*x_f[9 ]-x_f[10];
     Mb[8 ]=   -x_f[5 ]+ 6*x_f[6 ]-13*x_f[7 ]+20*x_f[8 ]-13*x_f[9 ]+6*x_f[10]-x_f[11];
     Mb[9 ]=   -x_f[6 ]+ 6*x_f[7 ]-13*x_f[8 ]+20*x_f[9 ]-13*x_f[10]+6*x_f[11]-x_f[12];
     Mb[10]=   -x_f[7 ]+ 6*x_f[8 ]-13*x_f[9 ]+20*x_f[10]-13*x_f[11]+6*x_f[12]-x_f[13];
     Mb[11]=   -x_f[8 ]+ 6*x_f[9 ]-13*x_f[10]+20*x_f[11]-13*x_f[12]+6*x_f[13]-x_f[14];
     Mb[12]=   -x_f[9 ]+ 6*x_f[10]-13*x_f[11]+20*x_f[12]-13*x_f[13]+6*x_f[14]-x_f[15];     
     Mb[13]=   -x_f[10]+ 6*x_f[11]-13*x_f[12]+20*x_f[13]-13*x_f[14]+6*x_f[15];
     Mb[14]=   -x_f[11]+ 6*x_f[12]-13*x_f[13]+20*x_f[14]-13*x_f[15];
     Mb[15]=   -x_f[12]+ 6*x_f[13]-13*x_f[14]+20*x_f[15];   
        
     SquareError = 0;        
     
     for(j=0; j<=15; j=j+1)begin     	  
       	if(b[j][15]==1)begin 
       		b_tmp= ~b[j]+1;
       		temp = b_tmp;
       		error= temp + Mb[j];
       	end
       	else begin
       		error = Mb[j] - b[j];
       	end
       	//$display(" Loop=%d    error= %.15f  \n", j, error);
     	  SquareError = SquareError + error*error;
     end
                   
     $display("-----------------------------------------------------\n");
     $display("        Your Output           Golden X\n");
     $display("  X1:     %.10f           2912.9564416992 \n", x_f[0 ]);
     $display("  X2:     %.10f           3563.4672138156 \n", x_f[1 ]);
     $display("  X3:     %.10f           1975.2084612612 \n", x_f[2 ]);
     $display("  X4:     %.10f           3160.3058219490 \n", x_f[3 ]);
     $display("  X5:     %.10f             91.0354695204 \n", x_f[4 ]);
     $display("  X6:     %.10f          -5435.9287723975 \n", x_f[5 ]);
     $display("  X7:     %.10f          -4893.7804543717 \n", x_f[6 ]);
     $display("  X8:     %.10f           1654.9085737604 \n", x_f[7 ]);
     $display("  X9:     %.10f           7008.1872681125 \n", x_f[8 ]);
     $display(" X10:     %.10f           5228.6840986953 \n", x_f[9 ]);
     $display(" X11:     %.10f           1204.3793848452 \n", x_f[10]);
     $display(" X12:     %.10f           3993.5629755645 \n", x_f[11]);
     $display(" X13:     %.10f           6128.9252357761 \n", x_f[12]);
     $display(" X14:     %.10f           3804.1421810991 \n", x_f[13]);
     $display(" X15:     %.10f            887.0698538670 \n", x_f[14]);
     $display(" X16:     %.10f          -1431.6509875273 \n", x_f[15]);          
     $display("-----------------------------------------------------\n");
     $display("So Your Error Ratio=  %.15f\n", SquareError);
     $display("-----------------------------------------------------\n");   
     
     error=SquareError;
     if(error<0.000001 && error!='hx && error!='hz)begin                           
         $display("Your Score Level: A \n");  
         $display("Congratulations! GSIM's Function Successfully!\n");
         $display("-------------------------PASS------------------------\n");
     end    
         
     else if(error>=0.000001 && error <0.000005 && error!='hx && error!='hz)begin
        $display("Your Score Level: B \n");
        $display("Congratulations! GSIM's Function Successfully!\n");
        $display("-------------------------PASS------------------------\n");
     end
     else if(error>=0.000005 && error <0.000010 && error!='hx && error!='hz)begin
        $display("Your Score Level: C \n");
        $display("Congratulations! GSIM's Function Successfully!\n");
        $display("-------------------------PASS------------------------\n");
     end 
     else if(error>=0.000010 && error <0.000050 && error!='hx && error!='hz)begin
        $display("Your Score Level: D \n");
        $display("Congratulations! GSIM's Function Successfully!\n");
        $display("-------------------------PASS------------------------\n");
     end 
        
     else if(error>=0.000050 && error <0.000100 && error!='hx && error!='hz)begin
        $display("Your Score Level: E \n");
        $display("Congratulations! GSIM's Function Successfully!\n");
        $display("-------------------------PASS------------------------\n");
     end     
     else if(error>=0.000100 && error <0.001000 && error!='hx && error!='hz)begin
        $display("Your Score Level: F \n");
        $display("Congratulations! GSIM's Function Successfully!\n");
        $display("-------------------------PASS------------------------\n");
     end 
     else if(error>=0.001000 && error <0.005000 && error!='hx && error!='hz)begin
        $display("Your Score Level: G \n");
        $display("Congratulations! GSIM's Function Successfully!\n");
        $display("-------------------------PASS------------------------\n");
     end 
     else if(error>=0.005000 && error <0.010000 && error!='hx && error!='hz)begin
        $display("Your Score Level: H \n");
        $display("Congratulations! GSIM's Function Successfully!\n");
        $display("-------------------------PASS------------------------\n");
     end 
     else if(error>=0.010000 && error <0.100000 && error!='hx && error!='hz)begin
        $display("Your Score Level: I \n");
        $display("Congratulations! GSIM's Function Successfully!\n");
        $display("-------------------------PASS------------------------\n");
     end 
     else if(error>=0.100000 && error <0.300000 && error!='hx && error!='hz)begin
        $display("Your Score Level: J \n");
        $display("Congratulations! GSIM's Function Successfully!\n");
        $display("-------------------------PASS------------------------\n");
     end 
     else begin
        $display("Your Score Level: K \n");                  
        $display("-------------   GSIM's Function Fail   -------------\n");
        $display("-------------------------Fail------------------------\n");
     end
      
      #(`CYCLE/2); $finish;
                       
end
   
endmodule

GSIM.vcd
$date
	Sat Apr 29 19:27:15 2023
$end
$version
	Icarus Verilog
$end
$timescale
	10ps
$end
$scope module test $end
$var wire 32 ! x_out [31:0] $end
$var wire 1 " out_valid $end
$var parameter 32 # N_PAT $end
$var reg 16 $ b_in [15:0] $end
$var reg 16 % b_tmp [15:0] $end
$var reg 1 & clk $end
$var reg 1 ' in_en $end
$var reg 1 ( reset $end
$var reg 1 ) stop $end
$var real 1 * SquareError $end
$var real 1 + error $end
$var integer 32 , i [31:0] $end
$var integer 32 - j [31:0] $end
$var integer 32 . loop [31:0] $end
$var integer 32 / out_f [31:0] $end
$var real 1 0 temp $end
$scope module GSIM $end
$var wire 16 1 b [15:0] $end
$var wire 16 2 b_in [15:0] $end
$var wire 1 & clk $end
$var wire 1 ' in_en $end
$var wire 1 ( reset $end
$var wire 32 3 x_out [31:0] $end
$var wire 32 4 x6 [31:0] $end
$var wire 32 5 x5 [31:0] $end
$var wire 32 6 x4 [31:0] $end
$var wire 32 7 x3 [31:0] $end
$var wire 32 8 x2 [31:0] $end
$var wire 32 9 x1 [31:0] $end
$var wire 32 : x [31:0] $end
$var wire 1 ; start $end
$var wire 1 " out_valid $end
$var parameter 32 < RUN $end
$var reg 4 = cycle_count_r [3:0] $end
$var reg 4 > cycle_count_w [3:0] $end
$var reg 6 ? run_count_r [5:0] $end
$var reg 6 @ run_count_w [5:0] $end
$scope module Computation_Unit $end
$var wire 32 A b [31:0] $end
$var wire 1 & clk $end
$var wire 1 ( reset $end
$var wire 32 B x_sub_6 [31:0] $end
$var wire 32 C x_plus_b [31:0] $end
$var wire 32 D x_new [31:0] $end
$var wire 32 E x_5 [31:0] $end
$var wire 32 F x_4_5 [31:0] $end
$var wire 32 G x_4 [31:0] $end
$var wire 32 H x_3 [31:0] $end
$var wire 32 I x_2_3_mul6 [31:0] $end
$var wire 32 J x_2_3_mul4 [31:0] $end
$var wire 32 K x_2_3_mul2 [31:0] $end
$var wire 32 L x_2_3 [31:0] $end
$var wire 32 M x_2 [31:0] $end
$var wire 32 N x_1 [31:0] $end
$var wire 32 O x_0_1_mul8 [31:0] $end
$var wire 32 P x_0_1_mul4 [31:0] $end
$var wire 32 Q x_0_1_mul13 [31:0] $end
$var wire 32 R x_0_1 [31:0] $end
$var wire 32 S x_0 [31:0] $end
$var wire 32 T DFF_nxt [31:0] $end
$var reg 32 U DFF [31:0] $end
$scope module div0 $end
$var wire 32 V in [31:0] $end
$var wire 34 W x_9_10 [33:0] $end
$var wire 34 X x_9 [33:0] $end
$var wire 34 Y x_6 [33:0] $end
$var wire 34 Z x_5to10 [33:0] $end
$var wire 34 [ x_5_6 [33:0] $end
$var wire 34 \ x_5 [33:0] $end
$var wire 34 ] x_26 [33:0] $end
$var wire 34 ^ x_25_26 [33:0] $end
$var wire 34 _ x_25 [33:0] $end
$var wire 34 ` x_22 [33:0] $end
$var wire 34 a x_21to26 [33:0] $end
$var wire 34 b x_21_22 [33:0] $end
$var wire 34 c x_21 [33:0] $end
$var wire 34 d x_18 [33:0] $end
$var wire 34 e x_17_18 [33:0] $end
$var wire 34 f x_17 [33:0] $end
$var wire 34 g x_14 [33:0] $end
$var wire 34 h x_13to18 [33:0] $end
$var wire 34 i x_13_14 [33:0] $end
$var wire 34 j x_13 [33:0] $end
$var wire 34 k x_10 [33:0] $end
$var wire 32 l out [31:0] $end
$upscope $end
$upscope $end
$scope module register_file $end
$var wire 16 m b_in [15:0] $end
$var wire 16 n b_out [15:0] $end
$var wire 1 & clk_in $end
$var wire 1 ' en_in $end
$var wire 1 ( rst_in $end
$var wire 32 o x_in [31:0] $end
$var wire 32 p x6_out [31:0] $end
$var wire 32 q x5_out [31:0] $end
$var wire 32 r x4_out [31:0] $end
$var wire 32 s x3_out [31:0] $end
$var wire 32 t x2_out [31:0] $end
$var wire 32 u x1_out [31:0] $end
$var wire 1 ; start_out $end
$var reg 4 v count_r [3:0] $end
$var reg 4 w count_w [3:0] $end
$var reg 1 x delay_start_r $end
$var reg 1 y delay_start_w $end
$var reg 1 ; start_r $end
$var reg 1 z start_w $end
$var integer 32 { i [31:0] $end
$upscope $end
$upscope $end
$upscope $end
$enddefinitions $end
$comment Show the parameter values. $end
$dumpall
b110010 <
b10000 #
$end
#0
$dumpvars
b1111 {
xz
xy
xx
bx w
bx v
bx u
bx t
bx s
bx r
bx q
bx p
bx o
bx n
bz m
bx l
bx k
bx j
bx i
bx h
bx g
bx f
bx e
bx d
bx c
bx b
bx a
bx `
bx _
bx ^
bx ]
bx \
bx [
bx Z
bx Y
bx X
bx W
bx V
bx U
bx T
bx S
bx R
bx Q
bx00 P
bx000 O
bx N
bx M
bx L
bx0 K
bx00 J
bx I
bx H
bx G
bx F
bx E
bx D
bx C
bx B
bx0000000000000000 A
bx @
bx ?
bx >
bx =
x;
bx :
bx 9
bx 8
bx 7
bx 6
bx 5
bx 4
bx 3
bz 2
bx 1
r0 0
b10 /
b0 .
bx -
bx ,
r0 +
r0 *
0)
0(
0'
0&
bx %
bz $
x"
bx !
$end
#500
b1 w
b0 8
b0 N
b0 t
b0 6
b0 H
b0 r
b0 4
b0 E
b0 p
b0 v
b10000 {
1&
#600
b0 !
b0 3
b0 :
b0 D
b0 l
b0 o
0"
b0 I
b0 K
b0 J
b0 Q
b0 P
b0 O
b0 Z
b0 [
b0 \
b0 Y
b0 W
b0 X
b0 k
b0 h
b0 i
b0 j
b0 g
b0 e
b0 f
b0 d
b0 a
b0 b
b0 c
b0 `
b0 ^
b0 _
b0 ]
0y
0z
b0 F
b0 5
b0 G
b0 q
b0 L
b0 7
b0 M
b0 s
b0 R
b0 9
b0 S
b0 u
b10000 {
b0 U
b0 V
0x
0;
1(
#1000
0&
#1500
b10000 {
1&
#1600
0(
#2000
0&
#2500
bx !
bx 3
bx :
bx D
bx l
bx o
bx \
bx [
bx Y
bx X
bx Z
bx W
bx k
bx j
bx i
bx g
bx f
bx h
bx e
bx d
bx c
bx b
bx `
bx _
bx a
bx ^
bx ]
bx U
bx V
b10000 {
1&
#2600
b0 >
b0 @
b1111 {
1'
b11111000 $
b11111000 2
b11111000 m
b1 ,
#3000
0&
#3500
b10 w
b1 v
b0 ?
b0 =
b1111 {
1&
#3600
b1111 {
b10 ,
b1111110101010110 $
b1111110101010110 2
b1111110101010110 m
#4000
0&
#4500
b11 w
b10 v
b1111 {
1&
#4600
b1111 {
b11 ,
b110000010000110 $
b110000010000110 2
b110000010000110 m
#5000
0&
#5500
b100 w
b11 v
b1111 {
1&
#5600
b1111 {
b100 ,
b1101101001101000 $
b1101101001101000 2
b1101101001101000 m
#6000
0&
#6500
b101 w
b100 v
b1111 {
1&
#6600
b1111 {
b101 ,
b1111001100001111 $
b1111001100001111 2
b1111001100001111 m
#7000
0&
#7500
b110 w
b101 v
b1111 {
1&
#7600
b1111 {
b110 ,
b111011010101001 $
b111011010101001 2
b111011010101001 m
#8000
0&
#8500
b111 w
b110 v
b1111 {
1&
#8600
b1111 {
b111 ,
b1000101011010100 $
b1000101011010100 2
b1000101011010100 m
#9000
0&
#9500
b1000 w
b111 v
b1111 {
1&
#9600
b1111 {
b1000 ,
b111100100010011 $
b111100100010011 2
b111100100010011 m
#10000
0&
#10500
b1001 w
b1000 v
b1111 {
1&
#10600
b1111 {
b1001 ,
b1011000001110000 $
b1011000001110000 2
b1011000001110000 m
#11000
0&
#11500
b1010 w
b1001 v
b1111 {
1&
#11600
b1111 {
b1010 ,
b10101011001000 $
b10101011001000 2
b10101011001000 m
#12000
0&
#12500
b1011 w
b1010 v
b1111 {
1&
#12600
b1111 {
b1011 ,
b1011000100001 $
b1011000100001 2
b1011000100001 m
#13000
0&
#13500
b1100 w
b1011 v
b1111 {
1&
#13600
b1111 {
b1100 ,
b10110011010100 $
b10110011010100 2
b10110011010100 m
#14000
0&
#14500
b1101 w
b1100 v
b1111 {
1&
#14600
b1111 {
b1101 ,
b1101110001101100 $
b1101110001101100 2
b1101110001101100 m
#15000
0&
#15500
b1110 w
b1101 v
b1111 {
1&
#15600
b1111 {
b1110 ,
b1111011001010 $
b1111011001010 2
b1111011001010 m
#16000
0&
#16500
b1111 w
b1110 v
b1111 {
1&
#16600
b1111 {
b1111 ,
b100111110100111 $
b100111110100111 2
b100111110100111 m
#17000
0&
#17500
1z
b0 w
b1111 v
b1111 {
1&
#17600
b1111 {
b10000 ,
b1000010011101111 $
b1000010011101111 2
b1000010011101111 m
#18000
0&
#18500
1y
b1 w
1;
b0 v
b111110000000000000000000 T
b111110000000000000000000 B
b111110000000000000000000 C
b111110000000000000000000 A
b11111000 1
b11111000 n
b1111 {
1&
#18600
b1111 {
b1 >
bz $
bz 2
bz m
0'
#19000
0&
#19500
b11000110011001100101 !
b11000110011001100101 3
b11000110011001100101 :
b11000110011001100101 D
b11000110011001100101 l
b11000110011001100101 o
b10 w
b1100010110100000000000 Z
b1011101000000000000000 [
b111110000000000000000 \
b11111000000000000000 Y
b101110100000000000 W
b11111000000000000 X
b1111100000000000 k
b11000101101000 h
b10111010000000 i
b1111100000000 j
b111110000000 g
b1011101000 e
b111110000 f
b11111000 d
b101111 a
b101110 b
b11111 c
b1111 `
b1 ^
b1 _
b0 ]
b10 >
b1 v
1x
b111110000000000000000000 U
b111110000000000000000000 V
b1 =
b11111101010101100000000000000000 T
b11111101010101100000000000000000 B
b11111101010101100000000000000000 C
b11111101010101100000000000000000 A
b1111110101010110 1
b1111110101010110 n
b1110 {
1&
#20000
0&
#20500
b11111111110111011110011001100101 !
b11111111110111011110011001100101 3
b11111111110111011110011001100101 :
b11111111110111011110011001100101 D
b11111111110111011110011001100101 l
b11111111110111011110011001100101 o
b110001100110011001010 K
b10010100110011001011110 I
b1100011001100110010100 J
b1111111111101010101100000000000000 \
b1111111111100000000010000000000000 [
b1111111111110101010110000000000000 Y
b1111111111111110101010110000000000 X
b1111111111011110000010001000000000 Z
b1111111111111110000000001000000000 W
b1111111111111111010101011000000000 k
b1111111111111111111010101011000000 j
b1111111111111111111000000000100000 i
b1111111111111111111101010101100000 g
b1111111111111111111111101010101100 f
b1111111111111111110111100000100010 h
b1111111111111111111111100000000010 e
b1111111111111111111111110101010110 d
b1111111111111111111111111110101010 c
b1111111111111111111111111101111111 b
b1111111111111111111111111111010101 `
b1111111111111111111111111111111010 _
b1111111111111111111111111101110110 a
b1111111111111111111111111111110111 ^
b1111111111111111111111111111111101 ]
b11 w
b11000110011001100101 L
b11000110011001100101 6
b11000110011001100101 H
b11000110011001100101 r
b11 >
b11111101010101100000000000000000 U
b11111101010101100000000000000000 V
b10 v
b1100000001110111001100110100010 T
b1100000001110111001100110100010 B
b1100000100001100000000000000000 C
b1100000100001100000000000000000 A
b110000010000110 1
b110000010000110 n
b10 =
b1110 {
1&
#21000
0&
