attempt.v
`timescale 1ns/10ps
module GSIM ( clk, reset, in_en, b_in, out_valid, x_out);

    input   clk ;
    input   reset ;
    input   in_en;
    output  out_valid;
    input   [15:0]  b_in;
    output reg [31:0]  x_out;

    parameter RUN = 69; //after this run number, the out_valid will be pulled up

    wire [32-1:0] x;
    wire [32-1:0] x1, x2, x3, x4, x5, x6;
    wire [16-1:0] b;
    reg  [4-1:0]  cycle_count_r;
    reg  [4-1:0]  cycle_count_w;
    reg  [9-1:0]  run_count_r;
    reg  [9-1:0]  run_count_w;
    wire          start;
    reg  [32-1:0] x_stored_r[1:16];
    reg  [32-1:0] x_stored_w[1:16];

    integer       i;

    register_file register_file (
        .clk_in(clk),
        .rst_in(reset),
        .en_in(in_en),
        .b_in(b_in),
        .x_in(x),
        .b_out(b),
        .x1_out(x1),
        .x2_out(x2),
        .x3_out(x3),
        .x4_out(x4),
        .x5_out(x5),
        .x6_out(x6),
        .start_out(start)
    );

    Computation_Unit Computation_Unit (
        .clk(clk),
        .b({b, 16'd0}),
        .x_0(x1),
        .x_1(x2),
        .x_2(x3),
        .x_3(x4),
        .x_4(x5),
        .x_5(x6),
        .x_new(x)
    );

    //Handle cycle_count_r, initialize when in_en is high; otherwise, count the cycle number
    always @(*) begin
        if (in_en == 1'b1)
            cycle_count_w = 4'd0;
        else
            cycle_count_w = cycle_count_r + 1;
    end

    always @(posedge clk) begin
        cycle_count_r <= cycle_count_w;
    end

    //Handle run_count_r, initialize when in_en is high; otherwise, when cycle_count_r is 15, run_count_r + 1
    always @(*) begin
        if (in_en == 1'b1)
            run_count_w = 8'd0;
        else if (cycle_count_r == 4'd15)
            run_count_w = run_count_r + 1;
        else
            run_count_w = run_count_r;
    end

    always @(posedge clk) begin
        run_count_r <= run_count_w;
    end

    // assign x_out     = x; //just output the x computed
    always @(*) begin
        for (i = 1; i < 16+1; i = i + 1) begin
            x_stored_w[i] = x_stored_r[i];
        end
        if (start && ((run_count_r == RUN && cycle_count_r >= 4'd1) || (run_count_r == RUN + 1 && cycle_count_r == 4'd0))) begin
            x_stored_w[16] = x;
            for (i = 1; i < 16; i = i + 1) begin
                x_stored_w[i] = x_stored_r[i+1];
            end
        end
    end

    always @(posedge clk) begin
        for (i = 1; i < 16+1; i = i + 1) begin
            x_stored_r[i] <= x_stored_w[i];
        end
    end

    always @(*) begin
        case (cycle_count_r)//1 5 9 13 2 6 10 14 3 7 11 15 4 8 12 16
            4'd1:
                x_out =  x_stored_r[1];
            4'd2:
                x_out =  x_stored_r[5];
            4'd3:
                x_out =  x_stored_r[9];
            4'd4:
                x_out =  x_stored_r[13];
            4'd5:
                x_out =  x_stored_r[2];
            4'd6:
                x_out =  x_stored_r[6];
            4'd7:
                x_out =  x_stored_r[10];
            4'd8:
                x_out =  x_stored_r[14];
            4'd9:
                x_out =  x_stored_r[3];
            4'd10:
                x_out =  x_stored_r[7];
            4'd11:
                x_out =  x_stored_r[11];
            4'd12:
                x_out =  x_stored_r[15];
            4'd13:
                x_out =  x_stored_r[4];
            4'd14:
                x_out =  x_stored_r[8];
            4'd15:
                x_out =  x_stored_r[12];
            4'd0:
                x_out =  x_stored_r[16];
        endcase
    end

    assign out_valid = (start && ((run_count_r == RUN+1 && cycle_count_r >= 4'd1) || (run_count_r == RUN + 2 && cycle_count_r == 4'd0))) ? 1'b1 : 1'b0; //pulled up when run_count_r achieve RUN

endmodule

/*Register file, used for shiftedly outputing the needed x and b for computation unit*/
module register_file (
    clk_in,
    rst_in,
    en_in,
    b_in,
    x_in,
    b_out,
    x1_out,
    x2_out,
    x3_out,
    x4_out,
    x5_out,
    x6_out,
    start_out
);

    input               clk_in, rst_in, en_in;
    input      [16-1:0] b_in;
    input      [32-1:0] x_in;
    output     [16-1:0] b_out;
    output     [32-1:0] x1_out, x2_out, x3_out, x4_out, x5_out, x6_out;
    output              start_out;

    reg        [16-1:0] b_r[1:16];
    reg        [16-1:0] b_w[1:16];
    
    reg        [32-1:0] x_r[1:16]; //1 5 9 13 2 6 10 14 3 7 11 15 4 8 12 16
    reg        [32-1:0] x_w[1:16];

    reg        [4-1:0]  count_r;
    reg        [4-1:0]  count_w;

    reg                 start_r;
    reg                 start_w;

    reg                 delay_start_r;
    reg                 delay_start_w;

    integer             i;

    //Handle b_r, when en_in == 1'b1, read b_in and shift to lower index; otherwise, shift circularly
    always @(*) begin
        if (en_in == 1'b1) begin
            b_w[16] = b_in;
            for (i = 1; i < 16; i = i + 1) begin
                b_w[i] = b_r[i+1];
            end
        end
        else if (start_r == 1'b1 && delay_start_r == 1'b0) begin //b_r stored in this order 1 5 9 13 2 6 10 14 3 7 11 15 4 8 12 16
            b_w[1] = b_r[5];
            b_w[2] = b_r[9];
            b_w[3] = b_r[13];
            b_w[4] = b_r[2];
            b_w[5] = b_r[6];
            b_w[6] = b_r[10];
            b_w[7] = b_r[14];
            b_w[8] = b_r[3];
            b_w[9] = b_r[7];
            b_w[10] = b_r[11];
            b_w[11] = b_r[15];
            b_w[12] = b_r[4];
            b_w[13] = b_r[8];
            b_w[14] = b_r[12];
            b_w[15] = b_r[16];
            b_w[16] = b_r[1];
        end
        else begin
            b_w[16] = b_r[1];
            for (i = 1; i < 16; i = i + 1) begin
                b_w[i] = b_r[i+1];
            end
        end
    end

    always @(posedge clk_in) begin
        for (i = 1; i < 16+1; i = i + 1) begin
            b_r[i] <= b_w[i];
        end
    end

    //Handle x_r, when reset is high, reset to initial values; else store their values until start_r is high, note that the delay_start_r is due to the pipeline of computational unit.
    always @(*) begin
        if (delay_start_r == 1'b1) begin //shift and store x_in to x[14]
            x_w[16] = x_r[1];
            x_w[15] = x_in;
            for (i = 1; i < 16 - 1; i = i + 1) begin
                x_w[i] = x_r[i+1];
            end
        end
        else if (start_r == 1'b1) begin //shift but not store x_in
            x_w[16] = x_r[1];
            for (i = 1; i < 16; i = i + 1) begin
                x_w[i] = x_r[i+1];
            end
        end
        else begin
            for (i = 1; i < 16+1; i = i + 1) begin
                x_w[i] = x_r[i];
            end
        end
    end

    always @(posedge clk_in or posedge rst_in) begin
        if (rst_in == 1'b1) begin //Run initial_x_value_generator.py for random initial values
            x_r[1] <= 32'd0;
            x_r[2] <= 32'd0;
            x_r[3] <= 32'd0;
            x_r[4] <= 32'd0;
            x_r[5] <= 32'd0;
            x_r[6] <= 32'd0;
            x_r[7] <= 32'd0;
            x_r[8] <= 32'd0;
            x_r[9] <= 32'd0;
            x_r[10] <= 32'd0;
            x_r[11] <= 32'd0;
            x_r[12] <= 32'd0;
            x_r[13] <= 32'd0;
            x_r[14] <= 32'd0;
            x_r[15] <= 32'd0;
            x_r[16] <= 32'd0;
        end
        else begin
            for (i = 1; i < 16+1; i = i + 1) begin
                x_r[i] <= x_w[i];
            end
        end
    end

    //Handle count_r, start to count right after the moment en_in is pulled to high; before that, set to 0
    always @(*) begin
        count_w = count_r + 1;
    end

    always @(posedge clk_in or posedge rst_in) begin
        if (rst_in == 1'b1)
            count_r <= 4'd0;
        else if (start_r == 1'b1 || en_in == 1'b1)
            count_r <= count_w;
        else
            count_r <= 4'd0;
    end

    //Handle start_r, if en_in is high, the counter start, and if the counter arrives at 15, set start_r to shift x_r
    always @(*) begin
        if (count_r == 4'd15)
            start_w = 1'b1;
        else
            start_w = start_r;
    end

    always @(posedge clk_in or posedge rst_in) begin
        if (rst_in == 1'b1)
            start_r <= 1'b0;
        else
            start_r <= start_w;
    end

    //Handle delay_start_r, delayed from start_r by one cycle because of the computational unit delay
    always @(*) begin
        delay_start_w = start_r;
    end

    always @(posedge clk_in or posedge rst_in) begin
        if (rst_in == 1'b1)
            delay_start_r <= 1'b0;
        else
            delay_start_r <= delay_start_w;
    end

    assign b_out     = b_r[1];                               //always output b_r[1] and shift from higher index
    assign x1_out    = (count_r < 4'd12) ? x_r[5] :
                       (count_r < 4'd15) ? x_r[6] : 32'd0;
    assign x2_out    = (count_r > 4'd3) ? x_r[13] :
                       (count_r > 4'd0) ? x_r[12] : 32'd0;
    assign x3_out    = (count_r < 4'd8) ? x_r[9] :
                       (count_r != 4'd11 && count_r != 4'd15) ? x_r[10] : 32'd0;
    assign x4_out    = (count_r > 4'd7) ? x_r[9] :
                       (count_r != 4'd0 && count_r != 4'd4) ? x_r[8] : 32'd0;
    assign x5_out    = (count_r < 4'd4) ? x_r[13] :
                       (count_r != 4'd7 && count_r != 4'd11 && count_r != 4'd15) ? x_r[14] : 32'd0;
    assign x6_out    = (count_r > 4'd11) ? x_r[5] :
                       (count_r != 4'd8 && count_r != 4'd4 && count_r != 4'd0) ? x_r[4] : 32'd0;
    assign start_out = start_r;                              //To let GSIM know the out_valid can be pulled up

endmodule


/* ======== 說明 ========
以下的code是參考Exercise.pdf p.9 右下角的架構圖來完成的
不過我把他切成2個stage的pipeline，前後2個stage的critical path都差不多是連續4個32bit加法所要的時間
我自己測了幾個test pattern，答案是正確的(雖然不能百分百保證沒問題)，然後誤差也很小，看能不能達到rank A(不能就再改一下除法器)
 ================================*/

module Computation_Unit (clk, b, x_0, x_1, x_2, x_3, x_4, x_5, x_new); // compute the result in 2 cycles 
    input                clk;               // Compute : b + 13(x_0 + x_1) - 6(x_2 + x_3) + (x_4 + x_5)
    input signed  [31:0] b;                    
    input signed  [31:0] x_0, x_1, x_2, x_3, x_4, x_5;
    output signed [31:0] x_new;

    //================= Parameter Declaration ======================
    wire signed   [32:0] x_0_1, x_2_3, x_4_5, x_plus_b;
    wire signed   [33:0] x_2_3_mul2;
    wire signed   [34:0] x_0_1_mul4, x_2_3_mul4, x_2_3_mul6;
    wire signed   [35:0] x_0_1_mul8, x_0_1_mul13, x_sub_6;
    wire signed   [36:0] DFF_nxt;
    reg signed    [36:0] DFF;

    //===================== Combinational ==========================
    assign x_0_1 = x_0 + x_1;
    assign x_2_3 = x_2 + x_3;
    assign x_4_5 = x_4 + x_5;
    assign x_plus_b = x_4_5 + b;
    assign x_0_1_mul4 = {x_0_1, 2'b0};
    assign x_0_1_mul8 = {x_0_1, 3'b0};
    assign x_0_1_mul13 = x_0_1 + x_0_1_mul4 + x_0_1_mul8;
    assign x_2_3_mul2 = {x_2_3, 1'b0};
    assign x_2_3_mul4 = {x_2_3, 2'b0};
    assign x_2_3_mul6 = x_2_3_mul2 + x_2_3_mul4;
    assign x_sub_6 = x_plus_b - x_2_3_mul6;
    assign DFF_nxt = x_0_1_mul13 + x_sub_6;

    division_20 div0 (.in(DFF), .out(x_new));

    //======================= Sequential ===========================
    always @(posedge clk) begin
        DFF <= DFF_nxt;
    end

endmodule

module division_20 (in, out);  // multiply by (2^-5 + 2^-6 + 2^-9 + 2^-10 + 2^-13 + 2^-14 + 2^-17 + 2^-18 
    input  signed [36:0] in;   //            + 2^-21 + 2^-22 + 2^-25 + 2^-26 + 2^-29 + 2^-30 + 2^-33 + 2^-34)
    output signed [31:0] out;

    wire signed [36:0] x_5, x_6, x_9, x_10, x_13, x_14, x_17, x_18, x_21, x_22, x_25, x_26, x_29, x_30, x_33, x_34;
    wire signed [36:0] x_5_6, x_9_10, x_13_14, x_17_18, x_21_22, x_25_26, x_29_30, x_33_34;
    wire signed [36:0] x_5to10, x_13to18, x_21to26, x_29to34, x_5to18, x_21to34, x_total;

    assign x_5 = in;
    assign x_6 = in >>> 1;
    assign x_9 = in >>> 4;
    assign x_10 = in >>> 5;
    assign x_13 = in >>> 8;
    assign x_14 = in >>> 9;
    assign x_17 = in >>> 12;
    assign x_18 = in >>> 13; 
    assign x_21 = in >>> 16;
    assign x_22 = in >>> 17;
    assign x_25 = in >>> 20;
    assign x_26 = in >>> 21;
    assign x_29 = in >>> 24;
    assign x_30 = in >>> 25;
    assign x_33 = in >>> 28;
    assign x_34 = in >>> 29;

    assign x_5_6 = x_5 + x_6;
    assign x_9_10 = x_9 + x_10;
    assign x_13_14 = x_13 + x_14;
    assign x_17_18 = x_17 + x_18;
    assign x_21_22 = x_21 + x_22;
    assign x_25_26 = x_25 + x_26;
    assign x_29_30 = x_29 + x_30;
    assign x_33_34 = x_33 + x_34;

    assign x_5to10 = x_5_6 + x_9_10;
    assign x_13to18 = x_13_14 + x_17_18;
    assign x_21to26 = x_21_22 + x_25_26;
    assign x_29to34 = x_29_30 + x_33_34;

    assign x_5to18 = x_5to10 + x_13to18;
    assign x_21to34 = x_21to26 + x_29to34;

    assign x_total = x_5to18 + x_21to34;
    assign out = x_total[36:5] + x_total[4];
endmodule

testfixture2.v
`timescale 1ns/10ps
`define CYCLE    4           	         // Modify your clock period here
`define SDFFILE  "./GSIM_syn.sdf"	      // Modify your sdf file name
`define PAT      "./pattern2.dat"    
`define DEL      1
module test;
parameter N_PAT   = 16;

reg   clk ;
reg   reset ;
reg   in_en;
reg   [15:0]  b_in;
wire  out_valid;
wire  [31:0]  x_out;

reg   [15:0]  pat_mem   [0:N_PAT-1];
reg   [31:0]  x         [0:N_PAT-1];
reg   [15:0]  b         [0:N_PAT-1];
reg   [15:0]  b_tmp;
integer       loop, i, j, out_f;
reg           stop;
real  Mb [0:15];
real  x_f[0:15];
real  SquareError, error, temp;


   GSIM GSIM( .clk(clk), .reset(reset), .in_en(in_en), .b_in(b_in),
              .out_valid(out_valid), .x_out(x_out));
   

`ifdef SDF
   initial $sdf_annotate(`SDFFILE, GSIM);
`endif

initial	$readmemh (`PAT, pat_mem);


initial begin
   clk         = 1'b0;
   reset       = 1'b0;
   in_en       = 1'b0;   
   b_in        = 'hz;
   stop        = 1'b0;   
   loop        = 0;
end

always begin #(`CYCLE/2) clk = ~clk; end

initial begin
$dumpfile("GSIM.vcd");
$dumpvars;
//$fsdbDumpfile("GSIM.fsdb");
//$fsdbDumpvars;

   out_f = $fopen("out.dat");
   if (out_f == 0) begin
        $display("Output file open error !");
        $finish;
   end
end


initial begin
   @(posedge clk)  #`DEL  reset = 1'b1;
   #`CYCLE                reset = 1'b0;
   
   @(posedge clk)  #`DEL i=0;
    while (i < N_PAT) begin               
         b_in  = pat_mem[i];
         b[i]  = pat_mem[i];
         in_en = 1'b1;
         i=i+1;                  
      @(posedge clk); #`DEL; 
    end     
    in_en = 1'b0;  b_in=16'hz;
end


always @(posedge clk)begin
   if(loop <16)begin
      if(out_valid)begin
         x[loop]=x_out;
         loop=loop+1;
      end
   end
   else begin
         stop=1;
   end
end


initial begin
   @(posedge stop) 
     for (j=0;j<=15;j=j+1)begin
        if(x[j][31]==1) begin   x_f[j]=~x[j] +1'b1;    x_f[j] =-x_f[j]/65536;  end
        else            begin   x_f[j]= x[j];          x_f[j] = x_f[j]/65536;  end
     end
                          
     Mb[0 ]= 20*x_f[0 ]-13*x_f[1 ]+ 6*x_f[2 ]-   x_f[3 ];
     Mb[1 ]=-13*x_f[0 ]+20*x_f[1 ]-13*x_f[2 ]+ 6*x_f[3 ]-   x_f[4 ];
     Mb[2 ]=  6*x_f[0 ]-13*x_f[1 ]+20*x_f[2 ]-13*x_f[3 ]+ 6*x_f[4 ]-  x_f[5 ];      
     Mb[3 ]=   -x_f[0 ]+ 6*x_f[1 ]-13*x_f[2 ]+20*x_f[3 ]-13*x_f[4 ]+6*x_f[5 ]-x_f[6 ];      
     Mb[4 ]=   -x_f[1 ]+ 6*x_f[2 ]-13*x_f[3 ]+20*x_f[4 ]-13*x_f[5 ]+6*x_f[6 ]-x_f[7 ];
     Mb[5 ]=   -x_f[2 ]+ 6*x_f[3 ]-13*x_f[4 ]+20*x_f[5 ]-13*x_f[6 ]+6*x_f[7 ]-x_f[8 ];                    
     Mb[6 ]=   -x_f[3 ]+ 6*x_f[4 ]-13*x_f[5 ]+20*x_f[6 ]-13*x_f[7 ]+6*x_f[8 ]-x_f[9 ];
     Mb[7 ]=   -x_f[4 ]+ 6*x_f[5 ]-13*x_f[6 ]+20*x_f[7 ]-13*x_f[8 ]+6*x_f[9 ]-x_f[10];
     Mb[8 ]=   -x_f[5 ]+ 6*x_f[6 ]-13*x_f[7 ]+20*x_f[8 ]-13*x_f[9 ]+6*x_f[10]-x_f[11];
     Mb[9 ]=   -x_f[6 ]+ 6*x_f[7 ]-13*x_f[8 ]+20*x_f[9 ]-13*x_f[10]+6*x_f[11]-x_f[12];
     Mb[10]=   -x_f[7 ]+ 6*x_f[8 ]-13*x_f[9 ]+20*x_f[10]-13*x_f[11]+6*x_f[12]-x_f[13];
     Mb[11]=   -x_f[8 ]+ 6*x_f[9 ]-13*x_f[10]+20*x_f[11]-13*x_f[12]+6*x_f[13]-x_f[14];
     Mb[12]=   -x_f[9 ]+ 6*x_f[10]-13*x_f[11]+20*x_f[12]-13*x_f[13]+6*x_f[14]-x_f[15];     
     Mb[13]=   -x_f[10]+ 6*x_f[11]-13*x_f[12]+20*x_f[13]-13*x_f[14]+6*x_f[15];
     Mb[14]=   -x_f[11]+ 6*x_f[12]-13*x_f[13]+20*x_f[14]-13*x_f[15];
     Mb[15]=   -x_f[12]+ 6*x_f[13]-13*x_f[14]+20*x_f[15];   
        
     SquareError = 0;        
     
     for(j=0; j<=15; j=j+1)begin     	  
       	if(b[j][15]==1)begin 
       		b_tmp= ~b[j]+1;
       		temp = b_tmp;
       		error= temp + Mb[j];
       	end
       	else begin
       		error = Mb[j] - b[j];
       	end
       	//$display(" Loop=%d    error= %.15f  \n", j, error);
     	  SquareError = SquareError + error*error;
     end
                   
     $display("-----------------------------------------------------\n");
     $display("        Your Output           Golden X\n");
     $display("  X1:     %.10f           2912.9564416992 \n", x_f[0 ]);
     $display("  X2:     %.10f           3563.4672138156 \n", x_f[1 ]);
     $display("  X3:     %.10f           1975.2084612612 \n", x_f[2 ]);
     $display("  X4:     %.10f           3160.3058219490 \n", x_f[3 ]);
     $display("  X5:     %.10f             91.0354695204 \n", x_f[4 ]);
     $display("  X6:     %.10f          -5435.9287723975 \n", x_f[5 ]);
     $display("  X7:     %.10f          -4893.7804543717 \n", x_f[6 ]);
     $display("  X8:     %.10f           1654.9085737604 \n", x_f[7 ]);
     $display("  X9:     %.10f           7008.1872681125 \n", x_f[8 ]);
     $display(" X10:     %.10f           5228.6840986953 \n", x_f[9 ]);
     $display(" X11:     %.10f           1204.3793848452 \n", x_f[10]);
     $display(" X12:     %.10f           3993.5629755645 \n", x_f[11]);
     $display(" X13:     %.10f           6128.9252357761 \n", x_f[12]);
     $display(" X14:     %.10f           3804.1421810991 \n", x_f[13]);
     $display(" X15:     %.10f            887.0698538670 \n", x_f[14]);
     $display(" X16:     %.10f          -1431.6509875273 \n", x_f[15]);          
     $display("-----------------------------------------------------\n");
     $display("So Your Error Ratio=  %.15f\n", SquareError);
     $display("-----------------------------------------------------\n");   
     
     error=SquareError;
     if(error<0.000001 && error!='hx && error!='hz)begin                           
         $display("Your Score Level: A \n");  
         $display("Congratulations! GSIM's Function Successfully!\n");
         $display("-------------------------PASS------------------------\n");
     end    
         
     else if(error>=0.000001 && error <0.000005 && error!='hx && error!='hz)begin
        $display("Your Score Level: B \n");
        $display("Congratulations! GSIM's Function Successfully!\n");
        $display("-------------------------PASS------------------------\n");
     end
     else if(error>=0.000005 && error <0.000010 && error!='hx && error!='hz)begin
        $display("Your Score Level: C \n");
        $display("Congratulations! GSIM's Function Successfully!\n");
        $display("-------------------------PASS------------------------\n");
     end 
     else if(error>=0.000010 && error <0.000050 && error!='hx && error!='hz)begin
        $display("Your Score Level: D \n");
        $display("Congratulations! GSIM's Function Successfully!\n");
        $display("-------------------------PASS------------------------\n");
     end 
        
     else if(error>=0.000050 && error <0.000100 && error!='hx && error!='hz)begin
        $display("Your Score Level: E \n");
        $display("Congratulations! GSIM's Function Successfully!\n");
        $display("-------------------------PASS------------------------\n");
     end     
     else if(error>=0.000100 && error <0.001000 && error!='hx && error!='hz)begin
        $display("Your Score Level: F \n");
        $display("Congratulations! GSIM's Function Successfully!\n");
        $display("-------------------------PASS------------------------\n");
     end 
     else if(error>=0.001000 && error <0.005000 && error!='hx && error!='hz)begin
        $display("Your Score Level: G \n");
        $display("Congratulations! GSIM's Function Successfully!\n");
        $display("-------------------------PASS------------------------\n");
     end 
     else if(error>=0.005000 && error <0.010000 && error!='hx && error!='hz)begin
        $display("Your Score Level: H \n");
        $display("Congratulations! GSIM's Function Successfully!\n");
        $display("-------------------------PASS------------------------\n");
     end 
     else if(error>=0.010000 && error <0.100000 && error!='hx && error!='hz)begin
        $display("Your Score Level: I \n");
        $display("Congratulations! GSIM's Function Successfully!\n");
        $display("-------------------------PASS------------------------\n");
     end 
     else if(error>=0.100000 && error <0.300000 && error!='hx && error!='hz)begin
        $display("Your Score Level: J \n");
        $display("Congratulations! GSIM's Function Successfully!\n");
        $display("-------------------------PASS------------------------\n");
     end 
     else begin
        $display("Your Score Level: K \n");                  
        $display("-------------   GSIM's Function Fail   -------------\n");
        $display("-------------------------Fail------------------------\n");
     end
      
      #(`CYCLE/2); $finish;
                       
end
   
endmodule

GSIM.vcd
$date
	Sun Apr 30 18:27:58 2023
$end
$version
	Icarus Verilog
$end
$timescale
	10ps
$end
$scope module test $end
$var wire 32 ! x_out [31:0] $end
$var wire 1 " out_valid $end
$var parameter 32 # N_PAT $end
$var reg 16 $ b_in [15:0] $end
$var reg 16 % b_tmp [15:0] $end
$var reg 1 & clk $end
$var reg 1 ' in_en $end
$var reg 1 ( reset $end
$var reg 1 ) stop $end
$var real 1 * SquareError $end
$var real 1 + error $end
$var integer 32 , i [31:0] $end
$var integer 32 - j [31:0] $end
$var integer 32 . loop [31:0] $end
$var integer 32 / out_f [31:0] $end
$var real 1 0 temp $end
$scope module GSIM $end
$var wire 16 1 b [15:0] $end
$var wire 16 2 b_in [15:0] $end
$var wire 1 & clk $end
$var wire 1 ' in_en $end
$var wire 1 ( reset $end
$var wire 32 3 x6 [31:0] $end
$var wire 32 4 x5 [31:0] $end
$var wire 32 5 x4 [31:0] $end
$var wire 32 6 x3 [31:0] $end
$var wire 32 7 x2 [31:0] $end
$var wire 32 8 x1 [31:0] $end
$var wire 32 9 x [31:0] $end
$var wire 1 : start $end
$var wire 1 " out_valid $end
$var parameter 32 ; RUN $end
$var reg 4 < cycle_count_r [3:0] $end
$var reg 4 = cycle_count_w [3:0] $end
$var reg 9 > run_count_r [8:0] $end
$var reg 9 ? run_count_w [8:0] $end
$var reg 32 @ x_out [31:0] $end
$var integer 32 A i [31:0] $end
$scope module Computation_Unit $end
$var wire 32 B b [31:0] $end
$var wire 1 & clk $end
$var wire 36 C x_sub_6 [35:0] $end
$var wire 33 D x_plus_b [32:0] $end
$var wire 32 E x_new [31:0] $end
$var wire 32 F x_5 [31:0] $end
$var wire 33 G x_4_5 [32:0] $end
$var wire 32 H x_4 [31:0] $end
$var wire 32 I x_3 [31:0] $end
$var wire 35 J x_2_3_mul6 [34:0] $end
$var wire 35 K x_2_3_mul4 [34:0] $end
$var wire 34 L x_2_3_mul2 [33:0] $end
$var wire 33 M x_2_3 [32:0] $end
$var wire 32 N x_2 [31:0] $end
$var wire 32 O x_1 [31:0] $end
$var wire 36 P x_0_1_mul8 [35:0] $end
$var wire 35 Q x_0_1_mul4 [34:0] $end
$var wire 36 R x_0_1_mul13 [35:0] $end
$var wire 33 S x_0_1 [32:0] $end
$var wire 32 T x_0 [31:0] $end
$var wire 37 U DFF_nxt [36:0] $end
$var reg 37 V DFF [36:0] $end
$scope module div0 $end
$var wire 37 W in [36:0] $end
$var wire 37 X x_5 [36:0] $end
$var wire 37 Y x_total [36:0] $end
$var wire 37 Z x_9_10 [36:0] $end
$var wire 37 [ x_9 [36:0] $end
$var wire 37 \ x_6 [36:0] $end
$var wire 37 ] x_5to18 [36:0] $end
$var wire 37 ^ x_5to10 [36:0] $end
$var wire 37 _ x_5_6 [36:0] $end
$var wire 37 ` x_34 [36:0] $end
$var wire 37 a x_33_34 [36:0] $end
$var wire 37 b x_33 [36:0] $end
$var wire 37 c x_30 [36:0] $end
$var wire 37 d x_29to34 [36:0] $end
$var wire 37 e x_29_30 [36:0] $end
$var wire 37 f x_29 [36:0] $end
$var wire 37 g x_26 [36:0] $end
$var wire 37 h x_25_26 [36:0] $end
$var wire 37 i x_25 [36:0] $end
$var wire 37 j x_22 [36:0] $end
$var wire 37 k x_21to34 [36:0] $end
$var wire 37 l x_21to26 [36:0] $end
$var wire 37 m x_21_22 [36:0] $end
$var wire 37 n x_21 [36:0] $end
$var wire 37 o x_18 [36:0] $end
$var wire 37 p x_17_18 [36:0] $end
$var wire 37 q x_17 [36:0] $end
$var wire 37 r x_14 [36:0] $end
$var wire 37 s x_13to18 [36:0] $end
$var wire 37 t x_13_14 [36:0] $end
$var wire 37 u x_13 [36:0] $end
$var wire 37 v x_10 [36:0] $end
$var wire 32 w out [31:0] $end
$upscope $end
$upscope $end
$scope module register_file $end
$var wire 16 x b_in [15:0] $end
$var wire 16 y b_out [15:0] $end
$var wire 1 & clk_in $end
$var wire 1 ' en_in $end
$var wire 1 ( rst_in $end
$var wire 32 z x_in [31:0] $end
$var wire 32 { x6_out [31:0] $end
$var wire 32 | x5_out [31:0] $end
$var wire 32 } x4_out [31:0] $end
$var wire 32 ~ x3_out [31:0] $end
$var wire 32 !" x2_out [31:0] $end
$var wire 32 "" x1_out [31:0] $end
$var wire 1 : start_out $end
$var reg 4 #" count_r [3:0] $end
$var reg 4 $" count_w [3:0] $end
$var reg 1 %" delay_start_r $end
$var reg 1 &" delay_start_w $end
$var reg 1 : start_r $end
$var reg 1 '" start_w $end
$var integer 32 (" i [31:0] $end
$upscope $end
$upscope $end
$upscope $end
$enddefinitions $end
$comment Show the parameter values. $end
$dumpall
b1000101 ;
b10000 #
$end
#0
$dumpvars
b10000 ("
x'"
x&"
x%"
bx $"
bx #"
bx ""
bx !"
bx ~
bx }
bx |
bx {
bx z
bx y
bz x
bx w
bx v
bx u
bx t
bx s
bx r
bx q
bx p
bx o
bx n
bx m
bx l
bx k
bx j
bx i
bx h
bx g
bx f
bx e
bx d
bx c
bx b
bx a
bx `
bx _
bx ^
bx ]
bx \
bx [
bx Z
bx Y
bx X
bx W
bx V
bx U
bx T
bx S
bx R
bx00 Q
bx000 P
bx O
bx N
bx M
bx0 L
bx00 K
bx J
bx I
bx H
bx G
bx F
bx E
bx D
bx C
bx0000000000000000 B
bx A
bx @
bx ?
bx >
bx =
bx <
x:
bx 9
bx 8
bx 7
bx 6
bx 5
bx 4
bx 3
bz 2
bx 1
r0 0
b10 /
b0 .
bx -
bx ,
r0 +
r0 *
0)
0(
0'
0&
bx %
bz $
x"
bx !
$end
#500
b0 5
b0 I
b0 }
b0 3
b0 F
b0 {
b1 $"
b0 7
b0 O
b0 !"
b0 #"
b10001 A
b10001 ("
1&
#600
0"
0&"
0'"
b10001 A
b0 G
b0 4
b0 H
b0 |
b0 J
b0 L
b0 K
b0 M
b0 6
b0 N
b0 ~
b0 R
b0 Q
b0 P
b0 S
b0 8
b0 T
b0 ""
b10000 ("
0%"
0:
1(
#1000
0&
#1500
b10001 A
b10001 ("
1&
#1600
0(
#2000
0&
#2500
b10001 A
b10001 ("
1&
#2600
b0 =
b0 ?
b10000 ("
1'
b101011110001000 $
b101011110001000 2
b101011110001000 x
b1 ,
#3000
0&
#3500
b10 $"
b0 >
b0 <
b1 #"
b10001 A
b10000 ("
1&
#3600
b10000 ("
b10 ,
b101010100111010 $
b101010100111010 2
b101010100111010 x
#4000
0&
#4500
b11 $"
b10 #"
b10001 A
b10000 ("
1&
#4600
b10000 ("
b11 ,
b1100000110100110 $
b1100000110100110 2
b1100000110100110 x
#5000
0&
#5500
b100 $"
b11 #"
b10001 A
b10000 ("
1&
#5600
b10000 ("
b100 ,
b1110100001100 $
b1110100001100 2
b1110100001100 x
#6000
0&
#6500
b101 $"
b100 #"
b10001 A
b10000 ("
1&
#6600
b10000 ("
b101 ,
b1010100001110 $
b1010100001110 2
b1010100001110 x
#7000
0&
#7500
b110 $"
b101 #"
b10001 A
b10000 ("
1&
#7600
b10000 ("
b110 ,
b101001101110 $
b101001101110 2
b101001101110 x
#8000
0&
#8500
b111 $"
b110 #"
b10001 A
b10000 ("
1&
#8600
b10000 ("
b111 ,
b101111010110100 $
b101111010110100 2
b101111010110100 x
#9000
0&
#9500
b1000 $"
b111 #"
b10001 A
b10000 ("
1&
#9600
b10000 ("
b1000 ,
b1100001111001001 $
b1100001111001001 2
b1100001111001001 x
#10000
0&
#10500
b1001 $"
b1000 #"
b10001 A
b10000 ("
1&
#10600
b10000 ("
b1001 ,
b1101000101101101 $
b1101000101101101 2
b1101000101101101 x
#11000
0&
#11500
b1010 $"
b1001 #"
b10001 A
b10000 ("
1&
#11600
b10000 ("
b1010 ,
b1001111010000101 $
b1001111010000101 2
b1001111010000101 x
#12000
0&
#12500
b1011 $"
b1010 #"
b10001 A
b10000 ("
1&
#12600
b10000 ("
b1011 ,
b111000010011000 $
b111000010011000 2
b111000010011000 x
#13000
0&
#13500
b1100 $"
b1011 #"
b10001 A
b10000 ("
1&
#13600
b10000 ("
b1100 ,
b10010101000011 $
b10010101000011 2
b10010101000011 x
#14000
0&
#14500
b1101 $"
b1100 #"
b10001 A
b10000 ("
1&
#14600
b10000 ("
b1101 ,
b1111101010111110 $
b1111101010111110 2
b1111101010111110 x
#15000
0&
#15500
b1110 $"
b1101 #"
b10001 A
b10000 ("
1&
#15600
b10000 ("
b1110 ,
b10001110101010 $
b10001110101010 2
b10001110101010 x
#16000
0&
#16500
b1111 $"
b1110 #"
b10001 A
b10000 ("
1&
#16600
b10000 ("
b1111 ,
b101101110010 $
b101101110010 2
b101101110010 x
#17000
0&
#17500
1'"
b0 $"
b1111 #"
b10001 A
b10000 ("
1&
#17600
b10000 ("
b10000 ,
b10010110110110 $
b10010110110110 2
b10010110110110 x
#18000
0&
